.coveragerc
.editorconfig
.travis.yml
CHANGES.rst
CONTRIBUTORS.rst
MANIFEST.in
README.rst
bootstrap-buildout.py
buildout.cfg
setup.cfg
setup.py
travis.cfg
docs/LICENSE.GPL
docs/LICENSE.rst
docs/index.rst
src/collective/__init__.py
src/collective.pdfdocument.egg-info/PKG-INFO
src/collective.pdfdocument.egg-info/SOURCES.txt
src/collective.pdfdocument.egg-info/dependency_links.txt
src/collective.pdfdocument.egg-info/entry_points.txt
src/collective.pdfdocument.egg-info/namespace_packages.txt
src/collective.pdfdocument.egg-info/not-zip-safe
src/collective.pdfdocument.egg-info/requires.txt
src/collective.pdfdocument.egg-info/top_level.txt
src/collective/pdfdocument/__init__.py
src/collective/pdfdocument/configure.zcml
src/collective/pdfdocument/interfaces.py
src/collective/pdfdocument/setuphandlers.py
src/collective/pdfdocument/testing.py
src/collective/pdfdocument/utilities.py
src/collective/pdfdocument/browser/__init__.py
src/collective/pdfdocument/browser/configure.zcml
src/collective/pdfdocument/browser/overrides/.gitkeep
src/collective/pdfdocument/browser/static/.gitkeep
src/collective/pdfdocument/locales/collective.pdfdocument.pot
src/collective/pdfdocument/locales/update.sh
src/collective/pdfdocument/profiles/default/browserlayer.xml
src/collective/pdfdocument/profiles/default/metadata.xml
src/collective/pdfdocument/profiles/uninstall/browserlayer.xml
src/collective/pdfdocument/tests/__init__.py
src/collective/pdfdocument/tests/test_robot.py
src/collective/pdfdocument/tests/test_setup.py
src/collective/pdfdocument/tests/robot/test_example.robot